{
  "chaquopy-openblas": {
    "display_name": "OpenBLAS (системная)",
    "version": "0.2.20",
    "description": "Нативная библиотека линейной алгебры — обязательна для NumPy/SciPy",
    "category": "science",
    "size_mb": 3.5,
    "depends": [],
    "pip_name": "chaquopy_openblas",
    "pure_python": false,
    "libffi": true,
    "abis": {
      "arm64-v8a":   "https://chaquo.com/pypi-13.1/chaquopy-openblas/chaquopy_openblas-0.2.20-5-py3-none-android_21_arm64_v8a.whl",
      "armeabi-v7a": "https://chaquo.com/pypi-13.1/chaquopy-openblas/chaquopy_openblas-0.2.20-5-py3-none-android_16_armeabi_v7a.whl",
      "x86_64":      "https://chaquo.com/pypi-13.1/chaquopy-openblas/chaquopy_openblas-0.2.20-5-py3-none-android_21_x86_64.whl",
      "x86":         "https://chaquo.com/pypi-13.1/chaquopy-openblas/chaquopy_openblas-0.2.20-5-py3-none-android_16_x86.whl"
    }
  },
  "numpy": {
    "display_name": "NumPy",
    "version": "1.26.2",
    "description": "Многомерные массивы и математика высокой производительности",
    "category": "science",
    "size_mb": 4.8,
    "depends": ["chaquopy-openblas"],
    "pip_name": "numpy",
    "pure_python": false,
    "abis": {
      "arm64-v8a":   "https://chaquo.com/pypi-13.1/numpy/numpy-1.26.2-0-cp310-cp310-android_21_arm64_v8a.whl",
      "armeabi-v7a": "https://chaquo.com/pypi-13.1/numpy/numpy-1.26.2-0-cp310-cp310-android_21_armeabi_v7a.whl",
      "x86_64":      "https://chaquo.com/pypi-13.1/numpy/numpy-1.26.2-0-cp310-cp310-android_21_x86_64.whl",
      "x86":         "https://chaquo.com/pypi-13.1/numpy/numpy-1.26.2-0-cp310-cp310-android_21_x86.whl"
    }
  },
  "pytz": {
    "display_name": "pytz",
    "version": "2024.1",
    "description": "Временные зоны для Python — нужен для pandas",
    "category": "science",
    "size_mb": 0.5,
    "depends": [],
    "pip_name": "pytz",
    "pure_python": true,
    "pip_install": true
  },
  "python-dateutil": {
    "display_name": "python-dateutil",
    "version": "2.9.0",
    "description": "Расширенная работа с датами — нужен для pandas",
    "category": "science",
    "size_mb": 0.5,
    "depends": [],
    "pip_name": "python-dateutil",
    "pure_python": true,
    "pip_install": true
  },
  "pandas": {
    "display_name": "Pandas",
    "version": "2.1.3",
    "description": "Анализ и обработка табличных данных",
    "category": "science",
    "size_mb": 11.0,
    "depends": ["numpy", "pytz", "python-dateutil"],
    "pip_name": "pandas",
    "pure_python": false,
    "abis": {
      "arm64-v8a":   "https://chaquo.com/pypi-13.1/pandas/pandas-2.1.3-1-cp310-cp310-android_24_arm64_v8a.whl",
      "armeabi-v7a": "https://chaquo.com/pypi-13.1/pandas/pandas-2.1.3-1-cp310-cp310-android_24_armeabi_v7a.whl",
      "x86_64":      "https://chaquo.com/pypi-13.1/pandas/pandas-2.1.3-1-cp310-cp310-android_24_x86_64.whl",
      "x86":         "https://chaquo.com/pypi-13.1/pandas/pandas-2.1.3-1-cp310-cp310-android_24_x86.whl"
    }
  },
  "opencv-python": {
    "display_name": "OpenCV",
    "version": "4.5.1.48",
    "description": "Компьютерное зрение: камера, изображения, видео",
    "category": "vision",
    "size_mb": 8.6,
    "depends": ["numpy"],
    "pip_name": "cv2",
    "pure_python": false,
    "abis": {
      "arm64-v8a":   "https://chaquo.com/pypi-13.1/opencv-python/opencv_python-4.5.1.48-2-cp310-cp310-android_24_arm64_v8a.whl",
      "armeabi-v7a": "https://chaquo.com/pypi-13.1/opencv-python/opencv_python-4.5.1.48-2-cp310-cp310-android_24_armeabi_v7a.whl",
      "x86_64":      "https://chaquo.com/pypi-13.1/opencv-python/opencv_python-4.5.1.48-2-cp310-cp310-android_24_x86_64.whl",
      "x86":         "https://chaquo.com/pypi-13.1/opencv-python/opencv_python-4.5.1.48-2-cp310-cp310-android_24_x86.whl"
    }
  },
  "matplotlib": {
    "display_name": "Matplotlib",
    "version": "3.6.0",
    "description": "Построение графиков и диаграмм",
    "category": "visualization",
    "size_mb": 6.6,
    "depends": ["numpy"],
    "pip_name": "matplotlib",
    "pure_python": false,
    "abis": {
      "arm64-v8a":   "https://chaquo.com/pypi-13.1/matplotlib/matplotlib-3.6.0-0-cp310-cp310-android_21_arm64_v8a.whl",
      "armeabi-v7a": "https://chaquo.com/pypi-13.1/matplotlib/matplotlib-3.6.0-0-cp310-cp310-android_16_armeabi_v7a.whl",
      "x86_64":      "https://chaquo.com/pypi-13.1/matplotlib/matplotlib-3.6.0-0-cp310-cp310-android_21_x86_64.whl",
      "x86":         "https://chaquo.com/pypi-13.1/matplotlib/matplotlib-3.6.0-0-cp310-cp310-android_16_x86.whl"
    }
  },
  "pillow": {
    "display_name": "Pillow (PIL)",
    "version": "11.0.0",
    "description": "Обработка изображений: фильтры, трансформации, форматы",
    "category": "vision",
    "size_mb": 0.6,
    "depends": [],
    "pip_name": "PIL",
    "pure_python": false,
    "abis": {
      "arm64-v8a":   "https://chaquo.com/pypi-13.1/pillow/pillow-11.0.0-0-cp310-cp310-android_24_arm64_v8a.whl",
      "armeabi-v7a": "https://chaquo.com/pypi-13.1/pillow/pillow-11.0.0-0-cp310-cp310-android_24_armeabi_v7a.whl",
      "x86_64":      "https://chaquo.com/pypi-13.1/pillow/pillow-11.0.0-0-cp310-cp310-android_24_x86_64.whl",
      "x86":         "https://chaquo.com/pypi-13.1/pillow/pillow-11.0.0-0-cp310-cp310-android_24_x86.whl"
    }
  },
  "scikit-learn": {
    "display_name": "Scikit-Learn",
    "version": "1.3.2",
    "description": "Машинное обучение: классификация, регрессия, кластеризация",
    "category": "ml",
    "size_mb": 8.4,
    "depends": ["numpy"],
    "pip_name": "sklearn",
    "pure_python": false,
    "abis": {
      "arm64-v8a":   "https://chaquo.com/pypi-13.1/scikit-learn/scikit_learn-1.3.2-0-cp310-cp310-android_21_arm64_v8a.whl",
      "armeabi-v7a": "https://chaquo.com/pypi-13.1/scikit-learn/scikit_learn-1.3.2-1-cp310-cp310-android_21_armeabi_v7a.whl",
      "x86_64":      "https://chaquo.com/pypi-13.1/scikit-learn/scikit_learn-1.3.2-0-cp310-cp310-android_21_x86_64.whl",
      "x86":         "https://chaquo.com/pypi-13.1/scikit-learn/scikit_learn-1.3.2-0-cp310-cp310-android_21_x86.whl"
    }
  },
  "scipy": {
    "display_name": "SciPy",
    "version": "1.8.1",
    "description": "Научные вычисления: интегралы, уравнения, оптимизация",
    "category": "science",
    "size_mb": 19.0,
    "depends": ["numpy"],
    "pip_name": "scipy",
    "pure_python": false,
    "abis": {
      "arm64-v8a":   "https://chaquo.com/pypi-13.1/scipy/scipy-1.8.1-1-cp310-cp310-android_21_arm64_v8a.whl",
      "armeabi-v7a": "https://chaquo.com/pypi-13.1/scipy/scipy-1.8.1-1-cp310-cp310-android_21_armeabi_v7a.whl",
      "x86_64":      "https://chaquo.com/pypi-13.1/scipy/scipy-1.8.1-1-cp310-cp310-android_21_x86_64.whl",
      "x86":         "https://chaquo.com/pypi-13.1/scipy/scipy-1.8.1-1-cp310-cp310-android_21_x86.whl"
    }
  },
  "chaquopy-libffi": {
    "display_name": "libffi (системная)",
    "version": "3.3-2",
    "description": "Нативная библиотека libffi — нужна для cffi и cryptography",
    "category": "other",
    "size_mb": 0.1,
    "depends": [],
    "pip_name": "chaquopy_libffi",
    "pure_python": false,
    "libffi": true,
    "abis": {
      "arm64-v8a":   "https://chaquo.com/pypi-7.0/chaquopy-libffi/chaquopy_libffi-3.3-2-py3-none-android_21_arm64_v8a.whl",
      "armeabi-v7a": "https://chaquo.com/pypi-7.0/chaquopy-libffi/chaquopy_libffi-3.3-2-py3-none-android_16_armeabi_v7a.whl",
      "x86_64":      "https://chaquo.com/pypi-7.0/chaquopy-libffi/chaquopy_libffi-3.3-2-py3-none-android_21_x86_64.whl",
      "x86":         "https://chaquo.com/pypi-7.0/chaquopy-libffi/chaquopy_libffi-3.3-2-py3-none-android_16_x86.whl"
    }
  },
  "cffi": {
    "display_name": "cffi",
    "version": "1.17.1",
    "description": "C Foreign Function Interface — нужен для cryptography",
    "category": "other",
    "size_mb": 0.5,
    "depends": ["chaquopy-libffi"],
    "pip_name": "_cffi_backend",
    "pure_python": false,
    "abis": {
      "arm64-v8a":   "https://chaquo.com/pypi-13.1/cffi/cffi-1.17.1-1-cp310-cp310-android_24_arm64_v8a.whl",
      "armeabi-v7a": "https://chaquo.com/pypi-13.1/cffi/cffi-1.17.1-1-cp310-cp310-android_24_armeabi_v7a.whl",
      "x86_64":      "https://chaquo.com/pypi-13.1/cffi/cffi-1.17.1-1-cp310-cp310-android_24_x86_64.whl",
      "x86":         "https://chaquo.com/pypi-13.1/cffi/cffi-1.17.1-1-cp310-cp310-android_24_x86.whl"
    }
  },
  "cryptography": {
    "display_name": "Cryptography",
    "version": "42.0.8",
    "description": "Шифрование AES, RSA, TLS и другие криптографические примитивы",
    "category": "security",
    "size_mb": 1.1,
    "depends": ["cffi"],
    "pip_name": "cryptography",
    "pure_python": false,
    "abis": {
      "arm64-v8a":   "https://chaquo.com/pypi-13.1/cryptography/cryptography-42.0.8-0-cp310-cp310-android_24_arm64_v8a.whl",
      "armeabi-v7a": "https://chaquo.com/pypi-13.1/cryptography/cryptography-42.0.8-0-cp310-cp310-android_24_armeabi_v7a.whl",
      "x86_64":      "https://chaquo.com/pypi-13.1/cryptography/cryptography-42.0.8-0-cp310-cp310-android_24_x86_64.whl",
      "x86":         "https://chaquo.com/pypi-13.1/cryptography/cryptography-42.0.8-0-cp310-cp310-android_24_x86.whl"
    }
  },
  "psutil": {
    "display_name": "psutil",
    "version": "7.1.3",
    "description": "Мониторинг процессов, CPU, памяти, дисков",
    "category": "other",
    "size_mb": 0.2,
    "depends": [],
    "pip_name": "psutil",
    "pure_python": false,
    "abis": {
      "arm64-v8a":   "https://chaquo.com/pypi-13.1/psutil/psutil-7.1.3-0-cp310-cp310-android_24_arm64_v8a.whl",
      "armeabi-v7a": "https://chaquo.com/pypi-13.1/psutil/psutil-7.1.3-0-cp310-cp310-android_24_armeabi_v7a.whl",
      "x86_64":      "https://chaquo.com/pypi-13.1/psutil/psutil-7.1.3-0-cp310-cp310-android_24_x86_64.whl",
      "x86":         "https://chaquo.com/pypi-13.1/psutil/psutil-7.1.3-0-cp310-cp310-android_24_x86.whl"
    }
  }
}
